emcstream
